scaut/__init__.py
scaut/core/__init__.py
scaut/core/config.py
scaut/core/logger.py
scaut/elegant/__init__.py
scaut/elegant/checks.py
scaut/elegant/exceptions.py
scaut/elegant/utils.py
scaut/scan/__init__.py
scaut/scan/decorators.py
scaut/scan/exceptions.py
scaut/scan/utils.py
scaut-0.1.0.dist-info/licenses/LICENSE
scaut-0.1.0.dist-info/METADATA
scaut-0.1.0.dist-info/WHEEL
scaut-0.1.0.dist-info/top_level.txt
scaut-0.1.0.dist-info/RECORD
