Metadata-Version: 2.4
Name: scaut
Version: 0.1.0
Summary: Software package for the orchestration of accelerator experiments
Author-email: Vyacheslav Fedorov <slava.fuodorov@yandex.ru>
License: MIT
Project-URL: Homepage, https://github.com/fuodorov/scaut
Project-URL: Bug Tracker, https://github.com/fuodorov/scaut/issues
Project-URL: Documentation, https://github.com/fuodorov/scaut/wiki
Keywords: accelerator,physics,scan,elegant,beam
Classifier: Development Status :: 4 - Beta
Classifier: Intended Audience :: Science/Research
Classifier: License :: OSI Approved :: MIT License
Classifier: Programming Language :: Python :: 3
Classifier: Programming Language :: Python :: 3.7
Classifier: Programming Language :: Python :: 3.8
Classifier: Programming Language :: Python :: 3.9
Classifier: Programming Language :: Python :: 3.10
Classifier: Topic :: Scientific/Engineering :: Physics
Requires-Python: >=3.7
License-File: LICENSE
Requires-Dist: scipy
Requires-Dist: numpy
Requires-Dist: scikit-optimize
Requires-Dist: pandas
Requires-Dist: matplotlib
Requires-Dist: plotly
Requires-Dist: pyepics
Requires-Dist: jupyter
Requires-Dist: tqdm
Dynamic: license-file
